jawanndenn/__init__.py
jawanndenn/__main__.py
jawanndenn/asgi.py
jawanndenn/index.html
jawanndenn/markup.py
jawanndenn/metadata.py
jawanndenn/middleware.py
jawanndenn/models.py
jawanndenn/serializers.py
jawanndenn/settings.py
jawanndenn/urls.py
jawanndenn/wsgi.py
jawanndenn/management/__init__.py
jawanndenn/management/commands/__init__.py
jawanndenn/management/commands/prune_expired_polls.py
jawanndenn/management/commands/tests/__init__.py
jawanndenn/management/commands/tests/test_prune_expired_polls.py
jawanndenn/migrations/0001_initial.py
jawanndenn/migrations/0002_django_extensions_3_0_0.py
jawanndenn/migrations/0003_poll_expires_at.py
jawanndenn/migrations/0004_tribool_votes.py
jawanndenn/migrations/0005_remove_poll_equal_width.py
jawanndenn/migrations/__init__.py
jawanndenn/static/3rdparty/github-buttons-4.0.1/LICENSE.md
jawanndenn/static/3rdparty/github-buttons-4.0.1/docs/github-btn.html
jawanndenn/static/3rdparty/roboto-20/COPYING
jawanndenn/static/3rdparty/roboto-20/css/roboto.css
jawanndenn/static/3rdparty/roboto-20/fonts/roboto-v20-vietnamese_latin-ext_latin_greek-ext_greek_cyrillic-ext_cyrillic-100.eot
jawanndenn/static/3rdparty/roboto-20/fonts/roboto-v20-vietnamese_latin-ext_latin_greek-ext_greek_cyrillic-ext_cyrillic-100.svg
jawanndenn/static/3rdparty/roboto-20/fonts/roboto-v20-vietnamese_latin-ext_latin_greek-ext_greek_cyrillic-ext_cyrillic-100.ttf
jawanndenn/static/3rdparty/roboto-20/fonts/roboto-v20-vietnamese_latin-ext_latin_greek-ext_greek_cyrillic-ext_cyrillic-100.woff
jawanndenn/static/3rdparty/roboto-20/fonts/roboto-v20-vietnamese_latin-ext_latin_greek-ext_greek_cyrillic-ext_cyrillic-100.woff2
jawanndenn/static/3rdparty/roboto-20/fonts/roboto-v20-vietnamese_latin-ext_latin_greek-ext_greek_cyrillic-ext_cyrillic-100italic.eot
jawanndenn/static/3rdparty/roboto-20/fonts/roboto-v20-vietnamese_latin-ext_latin_greek-ext_greek_cyrillic-ext_cyrillic-100italic.svg
jawanndenn-4.0.0.dist-info/METADATA
jawanndenn-4.0.0.dist-info/WHEEL
jawanndenn-4.0.0.dist-info/entry_points.txt
jawanndenn-4.0.0.dist-info/top_level.txt
jawanndenn-4.0.0.dist-info/RECORD
