Metadata-Version: 2.4
Name: jawanndenn
Version: 4.0.0
Summary: Libre alternative to Doodle
Home-page: https://github.com/hartwork/jawanndenn
Author: Sebastian Pipping
Author-email: sebastian@pipping.org
License: AGPLv3+
Classifier: Development Status :: 4 - Beta
Classifier: Framework :: Django
Classifier: License :: OSI Approved :: GNU Affero General Public License v3 or later (AGPLv3+)
Classifier: Programming Language :: JavaScript
Classifier: Programming Language :: Python
Classifier: Programming Language :: Python :: 3
Classifier: Programming Language :: Python :: 3.9
Classifier: Programming Language :: Python :: 3.10
Classifier: Programming Language :: Python :: 3.11
Classifier: Programming Language :: Python :: 3.12
Classifier: Programming Language :: Python :: 3.13
Classifier: Programming Language :: Python :: 3 :: Only
Classifier: Topic :: Internet :: WWW/HTTP :: WSGI :: Application
Classifier: Topic :: Office/Business :: Scheduling
Requires-Python: >=3.9
Requires-Dist: django>=2.2.7
Requires-Dist: django-extensions>=2.2.5
Requires-Dist: django-ratelimit>=4.0.0
Requires-Dist: djangorestframework>=3.11.0
Requires-Dist: gunicorn>=20.0.4
Requires-Dist: gunicorn-color>=0.1.0
Requires-Dist: python-dateutil>=2.8.1
Requires-Dist: python-rapidjson>=1.0
Requires-Dist: PyYAML>=6.0.2
Provides-Extra: tests
Requires-Dist: factory-boy>=2.12.0; extra == "tests"
Requires-Dist: parameterized>=0.7.1; extra == "tests"
Dynamic: author
Dynamic: author-email
Dynamic: classifier
Dynamic: description
Dynamic: description-content-type
Dynamic: home-page
Dynamic: license
Dynamic: provides-extra
Dynamic: requires-dist
Dynamic: requires-python
Dynamic: summary
